[
  { "id": "women-1", "name": "Women Product 1", "price": 199, "image": "https://via.placeholder.com/150" },
  { "id": "women-2", "name": "Women Product 2", "price": 249, "image": "https://via.placeholder.com/150" },
  { "id": "women-3", "name": "Women Product 3", "price": 179, "image": "https://via.placeholder.com/150" },
  { "id": "women-4", "name": "Women Product 4", "price": 299, "image": "https://via.placeholder.com/150" },
  { "id": "women-5", "name": "Women Product 5", "price": 399, "image": "https://via.placeholder.com/150" },
  { "id": "women-6", "name": "Women Product 6", "price": 219, "image": "https://via.placeholder.com/150" },
  { "id": "women-7", "name": "Women Product 7", "price": 199, "image": "https://via.placeholder.com/150" },
  { "id": "women-8", "name": "Women Product 8", "price": 189, "image": "https://via.placeholder.com/150" },
  { "id": "women-9", "name": "Women Product 9", "price": 349, "image": "https://via.placeholder.com/150" },
  { "id": "women-10", "name": "Women Product 10", "price": 279, "image": "https://via.placeholder.com/150" },
  { "id": "women-11", "name": "Women Product 11", "price": 199, "image": "https://via.placeholder.com/150" },
  { "id": "women-12", "name": "Women Product 12", "price": 359, "image": "https://via.placeholder.com/150" },
  { "id": "women-13", "name": "Women Product 13", "price": 299, "image": "https://via.placeholder.com/150" },
  { "id": "women-14", "name": "Women Product 14", "price": 209, "image": "https://via.placeholder.com/150" },
  { "id": "women-15", "name": "Women Product 15", "price": 259, "image": "https://via.placeholder.com/150" },
  { "id": "women-16", "name": "Women Product 16", "price": 319, "image": "https://via.placeholder.com/150" },
  { "id": "women-17", "name": "Women Product 17", "price": 189, "image": "https://via.placeholder.com/150" },
  { "id": "women-18", "name": "Women Product 18", "price": 249, "image": "https://via.placeholder.com/150" },
  { "id": "women-19", "name": "Women Product 19", "price": 219, "image": "https://via.placeholder.com/150" },
  { "id": "women-20", "name": "Women Product 20", "price": 399, "image": "https://via.placeholder.com/150" },
  { "id": "women-21", "name": "Women Product 21", "price": 199, "image": "https://via.placeholder.com/150" },
  { "id": "women-22", "name": "Women Product 22", "price": 299, "image": "https://via.placeholder.com/150" },
  { "id": "women-23", "name": "Women Product 23", "price": 279, "image": "https://via.placeholder.com/150" },
  { "id": "women-24", "name": "Women Product 24", "price": 209, "image": "https://via.placeholder.com/150" },
  { "id": "women-25", "name": "Women Product 25", "price": 189, "image": "https://via.placeholder.com/150" },
  { "id": "women-26", "name": "Women Product 26", "price": 339, "image": "https://via.placeholder.com/150" },
  { "id": "women-27", "name": "Women Product 27", "price": 199, "image": "https://via.placeholder.com/150" },
  { "id": "women-28", "name": "Women Product 28", "price": 229, "image": "https://via.placeholder.com/150" },
  { "id": "women-29", "name": "Women Product 29", "price": 279, "image": "https://via.placeholder.com/150" },
  { "id": "women-30", "name": "Women Product 30", "price": 199, "image": "https://via.placeholder.com/150" },
  { "id": "women-31", "name": "Women Product 31", "price": 259, "image": "https://via.placeholder.com/150" },
  { "id": "women-32", "name": "Women Product 32", "price": 329, "image": "https://via.placeholder.com/150" },
  { "id": "women-33", "name": "Women Product 33", "price": 219, "image": "https://via.placeholder.com/150" },
  { "id": "women-34", "name": "Women Product 34", "price": 199, "image": "https://via.placeholder.com/150" },
  { "id": "women-35", "name": "Women Product 35", "price": 289, "image": "https://via.placeholder.com/150" },
  { "id": "women-36", "name": "Women Product 36", "price": 369, "image": "https://via.placeholder.com/150" },
  { "id": "women-37", "name": "Women Product 37", "price": 399, "image": "https://via.placeholder.com/150" },
  { "id": "women-38", "name": "Women Product 38", "price": 249, "image": "https://via.placeholder.com/150" },
  { "id": "women-39", "name": "Women Product 39", "price": 319, "image": "https://via.placeholder.com/150" },
  { "id": "women-40", "name": "Women Product 40", "price": 299, "image": "https://via.placeholder.com/150" }
]
